monoff/__init__.py
monoff/__main__.py
monoff-0.0.3.dist-info/LICENSE
monoff-0.0.3.dist-info/METADATA
monoff-0.0.3.dist-info/WHEEL
monoff-0.0.3.dist-info/top_level.txt
monoff-0.0.3.dist-info/RECORD
