Metadata-Version: 2.1
Name: monoff
Version: 0.0.3
Summary: Simple script to turn off all monitors
Home-page: https://github.com/mmiguel6288code/monoff
Author: Matthew Miguel
Author-email: mmiguel6288code@gmail.com
Maintainer: Matthew Miguel
Maintainer-email: mmiguel6288code@gmail.com
License: MIT
Keywords: monitors,power,dpms,monitor,off,turn off,power down
Platform: UNKNOWN
Classifier: Intended Audience :: End Users/Desktop
Classifier: License :: OSI Approved :: MIT License
Classifier: Natural Language :: English
Classifier: Operating System :: OS Independent
Classifier: Programming Language :: Python :: 3.5
Classifier: Programming Language :: Python :: Implementation :: CPython
